paves/__about__.py
paves/__init__.py
paves/image.py
paves/miner.py
paves/py.typed
paves/tables.py
paves/tables_detr.py
paves/text.py
paves-0.8.0.dist-info/METADATA
paves-0.8.0.dist-info/WHEEL
paves-0.8.0.dist-info/licenses/LICENSE.txt
paves-0.8.0.dist-info/RECORD
