Metadata-Version: 2.4
Name: paves
Version: 0.8.0
Summary: PDF, Analyse et Visualisation avancÉS
Project-URL: Documentation, https://github.com/dhdaines/paves#readme
Project-URL: Issues, https://github.com/dhdaines/paves/issues
Project-URL: Source, https://github.com/dhdaines/paves
Author-email: David Huggins-Daines <dhd@ecolingui.ca>
License-Expression: MIT
License-File: LICENSE.txt
Keywords: graphics,pdf
Classifier: Development Status :: 4 - Beta
Classifier: Intended Audience :: Developers
Classifier: Intended Audience :: Science/Research
Classifier: License :: OSI Approved :: MIT License
Classifier: Programming Language :: Python
Classifier: Programming Language :: Python :: 3 :: Only
Classifier: Programming Language :: Python :: 3.1
Classifier: Programming Language :: Python :: 3.8
Classifier: Programming Language :: Python :: 3.9
Classifier: Programming Language :: Python :: 3.10
Classifier: Programming Language :: Python :: 3.11
Classifier: Programming Language :: Python :: 3.12
Classifier: Programming Language :: Python :: Implementation :: CPython
Classifier: Programming Language :: Python :: Implementation :: PyPy
Requires-Python: >=3.8
Requires-Dist: pillow
Requires-Dist: playa-pdf>=0.9.0
Provides-Extra: detr
Requires-Dist: docling-ibm-models; extra == 'detr'
Provides-Extra: tatr
Requires-Dist: gmft; extra == 'tatr'
